spa_cli/__init__.py
spa_cli/__main__.py
spa_cli/cli.py
spa_cli/globals.py
spa_cli/projects_config/.gitkeep
spa_cli/src/endpoint/__init__.py
spa_cli/src/endpoint/endpoint.py
spa_cli/src/lambda_function/__init__.py
spa_cli/src/lambda_function/lambda_function.py
spa_cli/src/model/__init__.py
spa_cli/src/model/model.py
spa_cli/src/project/__init__.py
spa_cli/src/project/project.py
spa_cli/src/utils/build.py
spa_cli/src/utils/build_api_json.py
spa_cli/src/utils/build_local_api.py
spa_cli/src/utils/folders.py
spa_cli/src/utils/install_local_layers.py
spa_cli/src/utils/main_server.py
spa_cli/src/utils/openapi.json
spa_cli/src/utils/strings.py
spa_cli/src/utils/template_gen.py
spa_cli/src/utils/up_local_server.py
spa_cli-1.0.10.dist-info/METADATA
spa_cli-1.0.10.dist-info/WHEEL
spa_cli-1.0.10.dist-info/entry_points.txt
spa_cli-1.0.10.dist-info/RECORD
