Metadata-Version: 2.4
Name: spa-cli
Version: 1.0.10
Summary: Un cli para manejar proyectos serverless en aws con python
Author: David Cuy
Author-email: david.cuy.sanchez@gmail.com
Requires-Python: >=3.11,<4.0
Classifier: Programming Language :: Python :: 3
Classifier: Programming Language :: Python :: 3.11
Classifier: Programming Language :: Python :: 3.12
Classifier: Programming Language :: Python :: 3.13
Classifier: Programming Language :: Python :: 3.14
Requires-Dist: cookiecutter (>=2.6.0,<3.0.0)
Requires-Dist: pydantic (>=2.11.9,<3.0.0)
Requires-Dist: python-dotenv (>=1.1.1,<2.0.0)
Requires-Dist: setuptools (>=80.9.0,<81.0.0)
Requires-Dist: toml (>=0.10.2,<0.11.0)
Requires-Dist: tqdm (>=4.67.1,<5.0.0)
Requires-Dist: typer (>=0.19.1,<0.20.0)
Project-URL: Documentation, https://github.com/DavidCuy/spa-cli
Project-URL: Homepage, https://github.com/DavidCuy/spa-cli
Project-URL: Repository, https://github.com/DavidCuy/spa-cli
